binance_historical_data/__init__.py
binance_historical_data/data_dumper.py
binance_historical_data/logger.py
binance_historical_data-0.1.14.dist-info/LICENSE.txt
binance_historical_data-0.1.14.dist-info/WHEEL
binance_historical_data-0.1.14.dist-info/METADATA
binance_historical_data-0.1.14.dist-info/RECORD
