Metadata-Version: 2.1
Name: binance-historical-data
Version: 0.1.14
Summary: 
Home-page: https://github.com/stas-prokopiev/binance_historical_data
License: MIT
Author: stanislav
Author-email: stas.prokopiev@gmail.com
Requires-Python: >=3.7,<4.0
Classifier: License :: OSI Approved :: MIT License
Classifier: Programming Language :: Python :: 3
Classifier: Programming Language :: Python :: 3.10
Classifier: Programming Language :: Python :: 3.7
Classifier: Programming Language :: Python :: 3.8
Classifier: Programming Language :: Python :: 3.9
Requires-Dist: char (>=0.1.2,<0.2.0)
Requires-Dist: ipywidgets (>=7.6.5,<8.0.0)
Requires-Dist: mpire (>=2.3.3,<3.0.0)
Requires-Dist: tqdm (>=4.62.3,<5.0.0)
Project-URL: Repository, https://github.com/stas-prokopiev/binance_historical_data
